mum/cli.py
mum/command.py
mum/constants.py
mum/enums.py
mum/todo_file.py
pymum-0.4.0.dist-info/entry_points.txt
pymum-0.4.0.dist-info/METADATA
pymum-0.4.0.dist-info/LICENSE
pymum-0.4.0.dist-info/WHEEL
pymum-0.4.0.dist-info/RECORD
