Metadata-Version: 2.1
Name: pymum
Version: 0.4.0
Summary: Save your weekly progress.
Home-page: https://github.com/nikromen/mum
License: GPLv3
Author: Jiri Kyjovsky
Author-email: j1.kyjovsky@gmail.com
Maintainer: Jiří Kyjovský
Maintainer-email: j1.kyjovsky@gmail.com
Requires-Python: >=3.10,<4.0
Classifier: License :: Other/Proprietary License
Classifier: Programming Language :: Python :: 3
Classifier: Programming Language :: Python :: 3.10
Classifier: Programming Language :: Python :: 3.11
Requires-Dist: click (>=8.1.3,<9.0.0)
Requires-Dist: rich (>=12.6,<14.0)
Project-URL: Repository, https://github.com/nikromen/mum
